gitlab_clone/__init__.py
gitlab_clone/clonner.py
gitlab_clone-1.2.0.dist-info/AUTHORS.rst
gitlab_clone-1.2.0.dist-info/LICENSE
gitlab_clone-1.2.0.dist-info/METADATA
gitlab_clone-1.2.0.dist-info/WHEEL
gitlab_clone-1.2.0.dist-info/entry_points.txt
gitlab_clone-1.2.0.dist-info/top_level.txt
gitlab_clone-1.2.0.dist-info/RECORD
