Metadata-Version: 2.1
Name: gitlab-clone
Version: 1.2.0
Summary: Gitlab tool for recursive clone
Home-page: https://github.com/ArseniyAntonov/gitlab-group-clone
Author: Arseniy Antonov
Author-email: arseny.antonov@gmail.com
License: MIT license
Keywords: gitlab,gitlab-api
Classifier: Framework :: Pytest
Classifier: Development Status :: 2 - Pre-Alpha
Classifier: Intended Audience :: Developers
Classifier: License :: OSI Approved :: MIT License
Classifier: Natural Language :: English
Classifier: Programming Language :: Python :: 2
Classifier: Programming Language :: Python :: 2.7
Classifier: Programming Language :: Python :: 3
Classifier: Programming Language :: Python :: 3.4
Classifier: Programming Language :: Python :: 3.5
Classifier: Programming Language :: Python :: 3.6
Classifier: Programming Language :: Python :: 3.7
License-File: LICENSE
License-File: AUTHORS.rst
Requires-Dist: requests
